imputetspy/__init__.py
imputetspy/datasets.py
imputetspy/main.py
imputetspy/utils.py
imputetspy/data/__init__.py
imputetspy/data/tsAirgap.csv
imputetspy/data/tsHeating.txt
imputetspy/data/tsNH4.txt
imputetspy-0.1.4.dist-info/LICENSE
imputetspy-0.1.4.dist-info/METADATA
imputetspy-0.1.4.dist-info/WHEEL
imputetspy-0.1.4.dist-info/top_level.txt
imputetspy-0.1.4.dist-info/RECORD
